CHANGES.md
LICENSE.md
MANIFEST.in
README.md
awskit.sh
setup.py
libaws/__init__.py
libaws/awskit.py
libaws.egg-info/PKG-INFO
libaws.egg-info/SOURCES.txt
libaws.egg-info/dependency_links.txt
libaws.egg-info/entry_points.txt
libaws.egg-info/not-zip-safe
libaws.egg-info/requires.txt
libaws.egg-info/top_level.txt
libaws/base/__init__.py
libaws/base/basedb.py
libaws/base/callback.py
libaws/base/daemon.py
libaws/base/filerange.py
libaws/base/md5.py
libaws/base/platform.py
libaws/base/singleton.py
libaws/base/utils.py
libaws/common/__init__.py
libaws/common/boto.py
libaws/common/config.py
libaws/common/const.py
libaws/common/db.py
libaws/common/errorcode.py
libaws/common/fileobj.py
libaws/common/logger.py
libaws/common/sql.py
libaws/common/utils.py
libaws/common/mylogger/__init__.py
libaws/common/mylogger/consolecolor.py
libaws/common/mylogger/loghandler.py
libaws/demo/bucket_policy.json
libaws/demo/centos_gtxcloud_gfs.yml
libaws/demo/condor_efs_instance_config.yml
libaws/demo/condor_exceute_efs_instance_config.yml
libaws/demo/glusterfs_test.yml
libaws/demo/gtxcloud_condor_instance_config.yml
libaws/demo/gtxcloud_demo.yml
libaws/demo/gtxcloud_demo2.yml
libaws/demo/gtxcloud_gfs_test.yml
libaws/demo/gtxcloud_mfs_test.yml
libaws/demo/instance_config.yml
libaws/demo/mfs_test.yml
libaws/demo/route_config.yml
libaws/demo/run_gtxcloud_gfs.yml
libaws/demo/security_config.yml
libaws/demo/subnet_config.yml
libaws/demo/vpc_config.yml
libaws/ec2/__init__.py
libaws/ec2/adapter.py
libaws/ec2/fdisk.py
libaws/ec2/gateway.py
libaws/ec2/instance.py
libaws/ec2/route.py
libaws/ec2/security.py
libaws/ec2/subnet.py
libaws/ec2/vpc.py
libaws/ec2/data/default_ami_config.json
libaws/ec2/data/default_instance_config.yml
libaws/ec2/data/default_instance_region_ap-northeast-1_config.yml
libaws/ec2/data/default_instance_region_ap-northeast-2_config.yml
libaws/ec2/data/default_instance_region_ap-southeast-1_config.yml
libaws/ec2/data/default_instance_region_ap-southeast-2_config.yml
libaws/ec2/data/default_instance_region_eu-central-1_config.yml
libaws/ec2/data/default_instance_region_eu-west-1_config.yml
libaws/ec2/data/default_instance_region_sa-east-1_config.yml
