Metadata-Version: 1.1
Name: libaws
Version: 1.1.4
Summary: libaws is a program can implement amason web service ,such as download files from bucket
Home-page: https://gitlab.com/wekay102200/genetalk_libaws.git
Author: wukan
Author-email: kan.wu@gengtalks.com
License: Genetalks
Platform: UNKNOWN
Classifier: Development Status :: 4 - Beta
Classifier: Environment :: Console
Classifier: Operating System :: OS Independent
Classifier: Programming Language :: Python
Classifier: Topic :: Software Development :: Libraries :: Python Modules
Classifier: Programming Language :: Python :: 2.5
Classifier: Programming Language :: Python :: 2.6
Classifier: Programming Language :: Python :: 2.7
Classifier: Programming Language :: Python :: Implementation :: CPython
Classifier: Programming Language :: Python :: Implementation :: PyPy
